lite_logging/__init__.py
lite_logging/client.py
lite_logging/pubsub/v1.py
lite_logging/pubsub/v2.py
lite_logging_client-1.0.8.dist-info/METADATA
lite_logging_client-1.0.8.dist-info/WHEEL
lite_logging_client-1.0.8.dist-info/licenses/LICENSE
lite_logging_client-1.0.8.dist-info/RECORD
