Metadata-Version: 2.4
Name: lite-logging-client
Version: 1.0.8
Summary: Lite logging client.
Author-email: Ngoc-Do Tran <dotrann.1412@gmail.com>
License: MIT
License-File: LICENSE
Requires-Python: >=3.8
Requires-Dist: cryptography
Requires-Dist: httpx
